Metadata-Version: 1.0
Name: pydependencygrapher
Version: 1.1.1
Summary: Draws dependency graphs.
Home-page: https://github.com/joaoantonioverdade/pydependencygrapher
Author: João Rodrigues
Author-email: joao.rodrigues@di.fc.ul.pt
License: UNKNOWN
Platform: UNKNOWN
